thunder/__init__.py
thunder/benchmark.py
thunder/main.py
thunder/config/config.yaml
thunder/config/adaptation/frozen.yaml
thunder/config/adaptation/lora.yaml
thunder/config/ckpt_saving/save_best_ckpt_only.yaml
thunder/config/ckpt_saving/save_ckpts_all_epochs.yaml
thunder/config/data_loading/embedding_pre_loading.yaml
thunder/config/data_loading/image_pre_loading.yaml
thunder/config/data_loading/online_loading.yaml
thunder/config/dataset/bach.yaml
thunder/config/dataset/bracs.yaml
thunder/config/dataset/break_his.yaml
thunder/config/dataset/ccrcc.yaml
thunder/config/dataset/crc.yaml
thunder/config/dataset/esca.yaml
thunder/config/dataset/mhist.yaml
thunder/config/dataset/ocelot.yaml
thunder/config/dataset/pannuke.yaml
thunder/config/dataset/patch_camelyon.yaml
thunder/config/dataset/segpath_epithelial.yaml
thunder/config/dataset/segpath_lymphocytes.yaml
thunder/config/dataset/spider_breast.yaml
thunder/config/dataset/spider_colorectal.yaml
thunder/config/dataset/spider_skin.yaml
thunder/config/dataset/spider_thorax.yaml
thunder/config/dataset/tcga_crc_msi.yaml
thunder/config/dataset/tcga_tils.yaml
thunder/config/dataset/tcga_uniform.yaml
thunder/config/dataset/wilds.yaml
thunder/config/embedding_recomputing/no_recomp_embs.yaml
thunder/config/embedding_recomputing/recomp_embs.yaml
thunder/config/model_retraining/no_retrain_model.yaml
thunder/config/model_retraining/retrain_model.yaml
thunder/config/pretrained_model/clipvitbasepatch32.yaml
thunder/config/pretrained_model/clipvitlargepatch14.yaml
thunder/config/pretrained_model/conch.yaml
thunder/config/pretrained_model/dinov2base.yaml
thunder/config/pretrained_model/dinov2large.yaml
thunder/config/pretrained_model/dinov3vitb16pretrainlvd1689m.yaml
thunder/config/pretrained_model/dinov3vitl16pretrainlvd1689m.yaml
thunder/config/pretrained_model/dinov3vits16pretrainlvd1689m.yaml
thunder/config/pretrained_model/hiboub.yaml
thunder/config/pretrained_model/hiboul.yaml
thunder/config/pretrained_model/hoptimus0.yaml
thunder_bench-0.2.0.dist-info/licenses/LICENSE
thunder_bench-0.2.0.dist-info/METADATA
thunder_bench-0.2.0.dist-info/WHEEL
thunder_bench-0.2.0.dist-info/entry_points.txt
thunder_bench-0.2.0.dist-info/top_level.txt
thunder_bench-0.2.0.dist-info/RECORD
