Metadata-Version: 2.4
Name: thunder-bench
Version: 0.2.0
Summary: THUNDER: Tile-level Histopathology image UNDERstanding benchmark
License-Expression: CC-BY-4.0
Requires-Python: <3.14,>=3.10
License-File: LICENSE
Requires-Dist: einops>=0.8.1
Requires-Dist: einops_exts>=0.0.4
Requires-Dist: h5py>=3.12.1
Requires-Dist: huggingface-hub>=0.35.3
Requires-Dist: hydra-core>=1.3.2
Requires-Dist: ijson>=3.4.0
Requires-Dist: kornia>=0.8.0
Requires-Dist: matplotlib>=3.9.2
Requires-Dist: numpy>=1.26.4
Requires-Dist: opencv-python>=4.10.0.84
Requires-Dist: omegaconf>=2.3.0
Requires-Dist: pandas>=2.2.3
Requires-Dist: pillow>=11.0.0
Requires-Dist: plotly>=6.0.0
Requires-Dist: pydantic<2.12
Requires-Dist: scikit-learn>=1.6.1
Requires-Dist: sentencepiece>=0.2.1
Requires-Dist: timm>=1.0.13
Requires-Dist: torch>=2.6.0
Requires-Dist: torchaudio>=2.6.0
Requires-Dist: torchvision>=0.21.0
Requires-Dist: tqdm>=4.66.5
Requires-Dist: transformers>=4.57.1
Requires-Dist: typer>=0.20.0
Requires-Dist: wandb>=0.19.4
Requires-Dist: wilds>=2.0.0
Provides-Extra: dev
Requires-Dist: black>=25.1.0; extra == "dev"
Requires-Dist: isort>=6.0.1; extra == "dev"
Requires-Dist: mkdocs>=1.6.1; extra == "dev"
Requires-Dist: mkdocs-material>=9.6.11; extra == "dev"
Requires-Dist: mkdocstrings>=0.29.1; extra == "dev"
Requires-Dist: mkdocstrings-python>=1.16.10; extra == "dev"
Requires-Dist: pytest>=8.4.2; extra == "dev"
Dynamic: license-file
